{
	"MARAMURES": "MM",
	"SALAJ": "SJ",
	"SATU MARE": "SM",
	"ARGES": "AG",
	"CALARASI": "CL",
	"DAMBOVITA": "DB",
	"GIURGIU": "GR",
	"IALOMITA": "IL",
	"PRAHOVA": "PH",
	"TELEORMAN": "TR",
	"BRAILA": "BR",
	"BACAU": "BC",
	"CONSTANTA": "CT",
	"GALATI": "GL",
	"ILFOV": "IF",
	"ALBA": "AB",
	"BRASOV": "BV",
	"TULCEA": "TL",
	"VRANCEA": "VN",
	"DOLJ": "DJ",
	"GORJ": "GJ",
	"MEHEDINTI": "MH",
	"OLT": "OT",
	"VALCEA": "VL",
	"ARAD": "AR",
	"CARAS-SEVERIN": "CS",
	"HUNEDOARA": "HD",
	"TIMIS": "TM",
	"COVASNA": "CV",
	"HARGHITA": "HR",
	"MURES": "MS",
	"SIBIU": "SB",
	"BOTOSANI": "BT",
	"IASI": "IS",
	"NEAMT": "NT",
	"SUCEAVA": "SV",
	"BIHOR": "BH",
	"MUNICIPIUL BUCURESTI": "B",
	"VASLUI": "VS",
	"BISTRITA-NASAUD": "BN",
	"CLUJ": "CJ",
	"BUZAU": "BZ"
}
